{
  "ordre_mission": [
      {
          "id": 1,
          "num_odm": "636-1777",
          "destination": "Saint-Louis",
          "date_deb": "2024-02-25",
          "date_fin": "2024-03-01",
          "moyen_transport": "vehicule",
          "salarie": "Robyn Willis",
          "fonction": "Directeur",
          "direction": "Transport"
      },
      {
          "id": 2,
          "num_odm": "223-5886",
          "destination": "Ziguinchor",
          "date_deb": "2024-08-23",
          "date_fin": "2024-08-26",
          "moyen_transport": "avion",
          "salarie": "Angie Martinez",
          "fonction": "Responsable Logistique",
          "direction": "Distribution"
      },
      {
          "id": 3,
          "num_odm": "779-9259",
          "destination": "Saint-Louis",
          "date_deb": "2024-10-09",
          "date_fin": "2024-10-19",
          "moyen_transport": "avion",
          "salarie": "Russell Fernandez",
          "fonction": "Consultant",
          "direction": "Distribution"
      },
      {
          "id": 4,
          "num_odm": "857-8108",
          "destination": "Thiès",
          "date_deb": "2024-02-08",
          "date_fin": "2024-03-05",
          "moyen_transport": "bus",
          "salarie": "Robert Armstrong",
          "fonction": "Agent maîtrise",
          "direction": "Distribution"
      },
      {
          "id": 5,
          "num_odm": "953-8654",
          "destination": "Thiès",
          "date_deb": "2024-01-14",
          "date_fin": "2024-01-16",
          "moyen_transport": "train",
          "salarie": "Shannon Horn",
          "fonction": "Agent maîtrise",
          "direction": "DSI"
      },
      {
          "id": 6,
          "num_odm": "861-8737",
          "destination": "Saint-Louis",
          "date_deb": "2024-06-28",
          "date_fin": "2024-07-04",
          "moyen_transport": "bus",
          "salarie": "Paul Medina",
          "fonction": "Responsable Logistique",
          "direction": "DSI"
      },
      {
          "id": 7,
          "num_odm": "972-7063",
          "destination": "Diourbel",
          "date_deb": "2024-10-19",
          "date_fin": "2024-11-06",
          "moyen_transport": "vehicule",
          "salarie": "Dr. Robert Williams",
          "fonction": "Responsable Logistique",
          "direction": "Distribution"
      },
      {
          "id": 8,
          "num_odm": "332-3362",
          "destination": "Kaolack",
          "date_deb": "2024-10-07",
          "date_fin": "2024-10-09",
          "moyen_transport": "vehicule",
          "salarie": "Tammy Murphy",
          "fonction": "Agent maîtrise",
          "direction": "DSI"
      },
      {
          "id": 9,
          "num_odm": "469-2158",
          "destination": "Dakar",
          "date_deb": "2024-04-08",
          "date_fin": "2024-05-01",
          "moyen_transport": "vehicule",
          "salarie": "Jasmine Moreno",
          "fonction": "Responsable Logistique",
          "direction": "DSI"
      },
      {
          "id": 10,
          "num_odm": "764-8934",
          "destination": "Louga",
          "date_deb": "2024-06-16",
          "date_fin": "2024-06-30",
          "moyen_transport": "train",
          "salarie": "Whitney Allen",
          "fonction": "Responsable Logistique",
          "direction": "Distribution"
      },
      {
          "id": 11,
          "num_odm": "749-7559",
          "destination": "Kaolack",
          "date_deb": "2024-01-06",
          "date_fin": "2024-01-21",
          "moyen_transport": "bus",
          "salarie": "Sherri Contreras",
          "fonction": "Secrétaire",
          "direction": "Transport"
      },
      {
          "id": 12,
          "num_odm": "356-2569",
          "destination": "Dakar",
          "date_deb": "2024-07-31",
          "date_fin": "2024-08-11",
          "moyen_transport": "bus",
          "salarie": "Christopher Jarvis",
          "fonction": "Secrétaire",
          "direction": "DRH"
      },
      {
          "id": 13,
          "num_odm": "792-6536",
          "destination": "Louga",
          "date_deb": "2024-04-24",
          "date_fin": "2024-05-20",
          "moyen_transport": "avion",
          "salarie": "Logan Warren",
          "fonction": "Délégué",
          "direction": "DRH"
      },
      {
          "id": 14,
          "num_odm": "833-9493",
          "destination": "Kaolack",
          "date_deb": "2024-05-20",
          "date_fin": "2024-06-04",
          "moyen_transport": "bus",
          "salarie": "Justin Sellers",
          "fonction": "Agent maîtrise",
          "direction": "Distribution"
      },
      {
          "id": 15,
          "num_odm": "842-4849",
          "destination": "Diourbel",
          "date_deb": "2024-08-14",
          "date_fin": "2024-08-29",
          "moyen_transport": "bus",
          "salarie": "Samantha Martinez",
          "fonction": "Secrétaire",
          "direction": "DRH"
      },
      {
          "id": 16,
          "num_odm": "899-8651",
          "destination": "Dakar",
          "date_deb": "2024-04-11",
          "date_fin": "2024-05-07",
          "moyen_transport": "avion",
          "salarie": "Anthony Hill",
          "fonction": "Agent maîtrise",
          "direction": "DRH"
      },
      {
          "id": 17,
          "num_odm": "777-4043",
          "destination": "Louga",
          "date_deb": "2024-08-06",
          "date_fin": "2024-08-11",
          "moyen_transport": "train",
          "salarie": "Joseph Lopez",
          "fonction": "Agent maîtrise",
          "direction": "Transport"
      },
      {
          "id": 18,
          "num_odm": "987-7171",
          "destination": "Diourbel",
          "date_deb": "2024-11-21",
          "date_fin": "2024-12-14",
          "moyen_transport": "avion",
          "salarie": "Carl Moreno",
          "fonction": "Secrétaire",
          "direction": "DSI"
      },
      {
          "id": 19,
          "num_odm": "538-4171",
          "destination": "Thiès",
          "date_deb": "2024-10-01",
          "date_fin": "2024-10-15",
          "moyen_transport": "bus",
          "salarie": "Melinda Collins",
          "fonction": "Responsable Logistique",
          "direction": "DRH"
      },
      {
          "id": 20,
          "num_odm": "259-8235",
          "destination": "Kaolack",
          "date_deb": "2024-09-27",
          "date_fin": "2024-10-11",
          "moyen_transport": "train",
          "salarie": "Jimmy Dawson",
          "fonction": "Responsable Logistique",
          "direction": "Distribution"
      },
      {
          "id": 21,
          "num_odm": "419-1009",
          "destination": "Diourbel",
          "date_deb": "2024-06-07",
          "date_fin": "2024-06-26",
          "moyen_transport": "avion",
          "salarie": "Michelle Smith",
          "fonction": "Secrétaire",
          "direction": "Transport"
      },
      {
          "id": 22,
          "num_odm": "849-4129",
          "destination": "Tambacounda",
          "date_deb": "2024-06-14",
          "date_fin": "2024-06-25",
          "moyen_transport": "train",
          "salarie": "Amber Scott",
          "fonction": "Agent maîtrise",
          "direction": "DRH"
      },
      {
          "id": 23,
          "num_odm": "933-6554",
          "destination": "Ziguinchor",
          "date_deb": "2024-09-29",
          "date_fin": "2024-10-21",
          "moyen_transport": "train",
          "salarie": "Jason Zuniga",
          "fonction": "Directeur",
          "direction": "DSI"
      },
      {
          "id": 24,
          "num_odm": "987-5865",
          "destination": "Ziguinchor",
          "date_deb": "2024-08-18",
          "date_fin": "2024-09-02",
          "moyen_transport": "bus",
          "salarie": "Karen Johnson",
          "fonction": "Délégué",
          "direction": "DSI"
      },
      {
          "id": 25,
          "num_odm": "749-4096",
          "destination": "Thiès",
          "date_deb": "2024-05-12",
          "date_fin": "2024-06-05",
          "moyen_transport": "bus",
          "salarie": "Anne Pratt",
          "fonction": "Agent maîtrise",
          "direction": "DSI"
      },
      {
          "id": 26,
          "num_odm": "358-6293",
          "destination": "Louga",
          "date_deb": "2024-07-17",
          "date_fin": "2024-08-04",
          "moyen_transport": "vehicule",
          "salarie": "Mark Burke",
          "fonction": "Consultant",
          "direction": "Transport"
      },
      {
          "id": 27,
          "num_odm": "516-3994",
          "destination": "Dakar",
          "date_deb": "2024-08-07",
          "date_fin": "2024-08-31",
          "moyen_transport": "vehicule",
          "salarie": "Jason Hodges",
          "fonction": "Directeur",
          "direction": "Transport"
      },
      {
          "id": 28,
          "num_odm": "337-3204",
          "destination": "Kaolack",
          "date_deb": "2024-07-10",
          "date_fin": "2024-08-04",
          "moyen_transport": "train",
          "salarie": "Denise Griffin",
          "fonction": "Agent maîtrise",
          "direction": "Transport"
      },
      {
          "id": 29,
          "num_odm": "171-4628",
          "destination": "Thiès",
          "date_deb": "2024-11-28",
          "date_fin": "2024-12-09",
          "moyen_transport": "bus",
          "salarie": "Joseph Forbes",
          "fonction": "Directeur",
          "direction": "Distribution"
      },
      {
          "id": 30,
          "num_odm": "174-2253",
          "destination": "Ziguinchor",
          "date_deb": "2024-11-13",
          "date_fin": "2024-11-14",
          "moyen_transport": "vehicule",
          "salarie": "Tyler Krueger",
          "fonction": "Responsable Logistique",
          "direction": "DRH"
      },
      {
          "id": 31,
          "num_odm": "250-8700",
          "destination": "Saint-Louis",
          "date_deb": "2024-10-30",
          "date_fin": "2024-11-22",
          "moyen_transport": "bus",
          "salarie": "Dana Sampson",
          "fonction": "Directeur",
          "direction": "Distribution"
      },
      {
          "id": 32,
          "num_odm": "320-3653",
          "destination": "Saint-Louis",
          "date_deb": "2024-05-25",
          "date_fin": "2024-06-11",
          "moyen_transport": "train",
          "salarie": "Derek Perez",
          "fonction": "Consultant",
          "direction": "DRH"
      },
      {
          "id": 33,
          "num_odm": "927-4896",
          "destination": "Kaolack",
          "date_deb": "2024-09-12",
          "date_fin": "2024-09-16",
          "moyen_transport": "train",
          "salarie": "Sergio Owen",
          "fonction": "Responsable Logistique",
          "direction": "Transport"
      },
      {
          "id": 34,
          "num_odm": "214-8899",
          "destination": "Ziguinchor",
          "date_deb": "2024-09-19",
          "date_fin": "2024-09-25",
          "moyen_transport": "train",
          "salarie": "Christine Garrett",
          "fonction": "Agent maîtrise",
          "direction": "DRH"
      },
      {
          "id": 35,
          "num_odm": "316-8386",
          "destination": "Ziguinchor",
          "date_deb": "2024-05-13",
          "date_fin": "2024-06-04",
          "moyen_transport": "bus",
          "salarie": "Ellen Weeks",
          "fonction": "Responsable Logistique",
          "direction": "DSI"
      },
      {
          "id": 36,
          "num_odm": "331-4478",
          "destination": "Thiès",
          "date_deb": "2024-11-19",
          "date_fin": "2024-11-24",
          "moyen_transport": "vehicule",
          "salarie": "Elizabeth Jones",
          "fonction": "Directeur",
          "direction": "Distribution"
      },
      {
          "id": 37,
          "num_odm": "713-2317",
          "destination": "Louga",
          "date_deb": "2024-04-29",
          "date_fin": "2024-05-22",
          "moyen_transport": "train",
          "salarie": "Alison Knight",
          "fonction": "Consultant",
          "direction": "DSI"
      },
      {
          "id": 38,
          "num_odm": "836-8076",
          "destination": "Dakar",
          "date_deb": "2024-05-30",
          "date_fin": "2024-06-23",
          "moyen_transport": "train",
          "salarie": "Tiffany Gonzales",
          "fonction": "Consultant",
          "direction": "DRH"
      },
      {
          "id": 39,
          "num_odm": "769-3169",
          "destination": "Ziguinchor",
          "date_deb": "2024-07-13",
          "date_fin": "2024-08-12",
          "moyen_transport": "train",
          "salarie": "Adam Fisher",
          "fonction": "Délégué",
          "direction": "Distribution"
      },
      {
          "id": 40,
          "num_odm": "363-5532",
          "destination": "Ziguinchor",
          "date_deb": "2024-06-03",
          "date_fin": "2024-06-17",
          "moyen_transport": "train",
          "salarie": "Eric Rodriguez",
          "fonction": "Secrétaire",
          "direction": "DSI"
      },
      {
          "id": 41,
          "num_odm": "791-4758",
          "destination": "Dakar",
          "date_deb": "2024-08-20",
          "date_fin": "2024-08-26",
          "moyen_transport": "bus",
          "salarie": "Danielle Sheppard",
          "fonction": "Secrétaire",
          "direction": "DSI"
      },
      {
          "id": 42,
          "num_odm": "681-3792",
          "destination": "Diourbel",
          "date_deb": "2024-02-20",
          "date_fin": "2024-03-02",
          "moyen_transport": "avion",
          "salarie": "Susan Bowen",
          "fonction": "Secrétaire",
          "direction": "DRH"
      },
      {
          "id": 43,
          "num_odm": "419-7720",
          "destination": "Saint-Louis",
          "date_deb": "2024-05-14",
          "date_fin": "2024-06-12",
          "moyen_transport": "bus",
          "salarie": "Jonathan Jones",
          "fonction": "Agent maîtrise",
          "direction": "Distribution"
      },
      {
          "id": 44,
          "num_odm": "929-8060",
          "destination": "Kaolack",
          "date_deb": "2024-01-04",
          "date_fin": "2024-01-13",
          "moyen_transport": "avion",
          "salarie": "John Anderson",
          "fonction": "Consultant",
          "direction": "Distribution"
      },
      {
          "id": 45,
          "num_odm": "150-5467",
          "destination": "Kaolack",
          "date_deb": "2024-06-28",
          "date_fin": "2024-07-13",
          "moyen_transport": "vehicule",
          "salarie": "Nichole Morrison",
          "fonction": "Consultant",
          "direction": "DSI"
      },
      {
          "id": 46,
          "num_odm": "424-9564",
          "destination": "Diourbel",
          "date_deb": "2024-09-23",
          "date_fin": "2024-09-29",
          "moyen_transport": "vehicule",
          "salarie": "Tabitha Gutierrez",
          "fonction": "Responsable Logistique",
          "direction": "DSI"
      },
      {
          "id": 47,
          "num_odm": "165-7889",
          "destination": "Dakar",
          "date_deb": "2024-07-01",
          "date_fin": "2024-07-22",
          "moyen_transport": "bus",
          "salarie": "Terry White",
          "fonction": "Délégué",
          "direction": "Distribution"
      },
      {
          "id": 48,
          "num_odm": "731-5239",
          "destination": "Thiès",
          "date_deb": "2024-06-16",
          "date_fin": "2024-07-04",
          "moyen_transport": "bus",
          "salarie": "Justin Gonzalez",
          "fonction": "Délégué",
          "direction": "DRH"
      },
      {
          "id": 49,
          "num_odm": "674-6706",
          "destination": "Dakar",
          "date_deb": "2024-02-01",
          "date_fin": "2024-02-26",
          "moyen_transport": "vehicule",
          "salarie": "Lauren Pitts",
          "fonction": "Secrétaire",
          "direction": "Transport"
      },
      {
          "id": 50,
          "num_odm": "806-7301",
          "destination": "Dakar",
          "date_deb": "2024-04-13",
          "date_fin": "2024-05-06",
          "moyen_transport": "train",
          "salarie": "Tina Doyle",
          "fonction": "Directeur",
          "direction": "Distribution"
      },
      {
          "id": 51,
          "num_odm": "260-3417",
          "destination": "Thiès",
          "date_deb": "2024-07-15",
          "date_fin": "2024-08-02",
          "moyen_transport": "bus",
          "salarie": "Jermaine Bender",
          "fonction": "Secrétaire",
          "direction": "DSI"
      },
      {
          "id": 52,
          "num_odm": "738-7558",
          "destination": "Diourbel",
          "date_deb": "2024-03-10",
          "date_fin": "2024-03-29",
          "moyen_transport": "train",
          "salarie": "Dr. Karen Jones",
          "fonction": "Responsable Logistique",
          "direction": "Transport"
      },
      {
          "id": 53,
          "num_odm": "767-3082",
          "destination": "Diourbel",
          "date_deb": "2024-03-05",
          "date_fin": "2024-03-13",
          "moyen_transport": "avion",
          "salarie": "Deborah Bennett",
          "fonction": "Délégué",
          "direction": "DRH"
      },
      {
          "id": 54,
          "num_odm": "514-1033",
          "destination": "Diourbel",
          "date_deb": "2024-01-23",
          "date_fin": "2024-01-24",
          "moyen_transport": "train",
          "salarie": "Deborah Pearson",
          "fonction": "Secrétaire",
          "direction": "Distribution"
      },
      {
          "id": 55,
          "num_odm": "188-7007",
          "destination": "Kaolack",
          "date_deb": "2024-06-27",
          "date_fin": "2024-07-14",
          "moyen_transport": "vehicule",
          "salarie": "Michael Pearson",
          "fonction": "Consultant",
          "direction": "Transport"
      },
      {
          "id": 56,
          "num_odm": "410-2379",
          "destination": "Ziguinchor",
          "date_deb": "2024-02-12",
          "date_fin": "2024-02-28",
          "moyen_transport": "train",
          "salarie": "Holly Fitzpatrick",
          "fonction": "Secrétaire",
          "direction": "DSI"
      },
      {
          "id": 57,
          "num_odm": "573-1257",
          "destination": "Tambacounda",
          "date_deb": "2024-10-01",
          "date_fin": "2024-10-28",
          "moyen_transport": "train",
          "salarie": "Mark Tyler",
          "fonction": "Agent maîtrise",
          "direction": "DRH"
      },
      {
          "id": 58,
          "num_odm": "334-9056",
          "destination": "Dakar",
          "date_deb": "2024-05-01",
          "date_fin": "2024-05-11",
          "moyen_transport": "bus",
          "salarie": "Rhonda Wilson",
          "fonction": "Secrétaire",
          "direction": "Distribution"
      },
      {
          "id": 59,
          "num_odm": "770-6637",
          "destination": "Dakar",
          "date_deb": "2024-07-24",
          "date_fin": "2024-08-16",
          "moyen_transport": "train",
          "salarie": "James Pacheco",
          "fonction": "Responsable Logistique",
          "direction": "DSI"
      },
      {
          "id": 60,
          "num_odm": "128-9452",
          "destination": "Kaolack",
          "date_deb": "2024-04-23",
          "date_fin": "2024-05-08",
          "moyen_transport": "vehicule",
          "salarie": "Heather Johnson",
          "fonction": "Délégué",
          "direction": "Transport"
      },
      {
          "id": 61,
          "num_odm": "519-2768",
          "destination": "Ziguinchor",
          "date_deb": "2024-11-20",
          "date_fin": "2024-12-10",
          "moyen_transport": "avion",
          "salarie": "Matthew Peters",
          "fonction": "Directeur",
          "direction": "Distribution"
      },
      {
          "id": 62,
          "num_odm": "440-5662",
          "destination": "Kaolack",
          "date_deb": "2024-10-27",
          "date_fin": "2024-10-28",
          "moyen_transport": "vehicule",
          "salarie": "Erika Henderson",
          "fonction": "Secrétaire",
          "direction": "Distribution"
      },
      {
          "id": 63,
          "num_odm": "808-9055",
          "destination": "Thiès",
          "date_deb": "2024-04-19",
          "date_fin": "2024-05-04",
          "moyen_transport": "bus",
          "salarie": "Mandy Lara",
          "fonction": "Agent maîtrise",
          "direction": "DRH"
      },
      {
          "id": 64,
          "num_odm": "299-6956",
          "destination": "Ziguinchor",
          "date_deb": "2024-08-03",
          "date_fin": "2024-08-04",
          "moyen_transport": "vehicule",
          "salarie": "Dominique Cervantes",
          "fonction": "Secrétaire",
          "direction": "DRH"
      },
      {
          "id": 65,
          "num_odm": "601-7658",
          "destination": "Louga",
          "date_deb": "2024-06-04",
          "date_fin": "2024-06-22",
          "moyen_transport": "bus",
          "salarie": "Paul George",
          "fonction": "Responsable Logistique",
          "direction": "Transport"
      },
      {
          "id": 66,
          "num_odm": "487-5325",
          "destination": "Tambacounda",
          "date_deb": "2024-09-23",
          "date_fin": "2024-10-13",
          "moyen_transport": "train",
          "salarie": "Kevin Smith DDS",
          "fonction": "Secrétaire",
          "direction": "DRH"
      },
      {
          "id": 67,
          "num_odm": "538-6911",
          "destination": "Kaolack",
          "date_deb": "2024-07-01",
          "date_fin": "2024-07-20",
          "moyen_transport": "vehicule",
          "salarie": "Timothy Roberts",
          "fonction": "Consultant",
          "direction": "DRH"
      },
      {
          "id": 68,
          "num_odm": "652-1803",
          "destination": "Ziguinchor",
          "date_deb": "2024-04-25",
          "date_fin": "2024-05-24",
          "moyen_transport": "bus",
          "salarie": "Sean Anderson",
          "fonction": "Délégué",
          "direction": "Distribution"
      },
      {
          "id": 69,
          "num_odm": "265-7443",
          "destination": "Saint-Louis",
          "date_deb": "2024-04-04",
          "date_fin": "2024-04-15",
          "moyen_transport": "vehicule",
          "salarie": "Jerry Day",
          "fonction": "Directeur",
          "direction": "Distribution"
      },
      {
          "id": 70,
          "num_odm": "221-9570",
          "destination": "Thiès",
          "date_deb": "2024-05-31",
          "date_fin": "2024-06-07",
          "moyen_transport": "avion",
          "salarie": "Stephanie Pratt",
          "fonction": "Directeur",
          "direction": "Transport"
      },
      {
          "id": 71,
          "num_odm": "365-6257",
          "destination": "Thiès",
          "date_deb": "2024-06-18",
          "date_fin": "2024-07-08",
          "moyen_transport": "train",
          "salarie": "Melissa White",
          "fonction": "Directeur",
          "direction": "DSI"
      },
      {
          "id": 72,
          "num_odm": "403-9882",
          "destination": "Dakar",
          "date_deb": "2024-02-21",
          "date_fin": "2024-02-23",
          "moyen_transport": "bus",
          "salarie": "Erin Bowman MD",
          "fonction": "Responsable Logistique",
          "direction": "DSI"
      },
      {
          "id": 73,
          "num_odm": "979-7536",
          "destination": "Kaolack",
          "date_deb": "2024-09-12",
          "date_fin": "2024-09-18",
          "moyen_transport": "bus",
          "salarie": "Bobby Boone",
          "fonction": "Secrétaire",
          "direction": "Transport"
      },
      {
          "id": 74,
          "num_odm": "409-2448",
          "destination": "Ziguinchor",
          "date_deb": "2024-10-11",
          "date_fin": "2024-10-22",
          "moyen_transport": "avion",
          "salarie": "Anthony Carroll",
          "fonction": "Agent maîtrise",
          "direction": "DSI"
      },
      {
          "id": 75,
          "num_odm": "675-3994",
          "destination": "Kaolack",
          "date_deb": "2024-07-15",
          "date_fin": "2024-07-31",
          "moyen_transport": "train",
          "salarie": "Miss Jacqueline Burke DDS",
          "fonction": "Directeur",
          "direction": "DSI"
      },
      {
          "id": 76,
          "num_odm": "544-8076",
          "destination": "Louga",
          "date_deb": "2024-12-18",
          "date_fin": "2025-01-12",
          "moyen_transport": "vehicule",
          "salarie": "Kimberly Johnson",
          "fonction": "Délégué",
          "direction": "Distribution"
      },
      {
          "id": 77,
          "num_odm": "283-7186",
          "destination": "Kaolack",
          "date_deb": "2024-01-06",
          "date_fin": "2024-01-08",
          "moyen_transport": "train",
          "salarie": "Michael Castro",
          "fonction": "Consultant",
          "direction": "Transport"
      },
      {
          "id": 78,
          "num_odm": "416-4905",
          "destination": "Tambacounda",
          "date_deb": "2024-08-24",
          "date_fin": "2024-09-05",
          "moyen_transport": "avion",
          "salarie": "Jeffery Klein",
          "fonction": "Consultant",
          "direction": "DSI"
      },
      {
          "id": 79,
          "num_odm": "823-4487",
          "destination": "Louga",
          "date_deb": "2024-01-17",
          "date_fin": "2024-02-02",
          "moyen_transport": "bus",
          "salarie": "Mary White",
          "fonction": "Directeur",
          "direction": "Distribution"
      },
      {
          "id": 80,
          "num_odm": "966-8176",
          "destination": "Ziguinchor",
          "date_deb": "2024-12-12",
          "date_fin": "2025-01-07",
          "moyen_transport": "train",
          "salarie": "Jessica Ortiz",
          "fonction": "Agent maîtrise",
          "direction": "Distribution"
      },
      {
          "id": 81,
          "num_odm": "469-9599",
          "destination": "Ziguinchor",
          "date_deb": "2024-11-27",
          "date_fin": "2024-12-12",
          "moyen_transport": "train",
          "salarie": "Margaret Stout",
          "fonction": "Agent maîtrise",
          "direction": "Distribution"
      },
      {
          "id": 82,
          "num_odm": "740-3312",
          "destination": "Ziguinchor",
          "date_deb": "2024-10-22",
          "date_fin": "2024-11-13",
          "moyen_transport": "avion",
          "salarie": "Todd Henderson",
          "fonction": "Délégué",
          "direction": "Transport"
      },
      {
          "id": 83,
          "num_odm": "380-7060",
          "destination": "Ziguinchor",
          "date_deb": "2024-06-06",
          "date_fin": "2024-07-03",
          "moyen_transport": "bus",
          "salarie": "Robert Lin",
          "fonction": "Consultant",
          "direction": "DRH"
      },
      {
          "id": 84,
          "num_odm": "959-3620",
          "destination": "Thiès",
          "date_deb": "2024-04-16",
          "date_fin": "2024-05-16",
          "moyen_transport": "bus",
          "salarie": "Renee Gay",
          "fonction": "Consultant",
          "direction": "Distribution"
      },
      {
          "id": 85,
          "num_odm": "444-7654",
          "destination": "Kaolack",
          "date_deb": "2024-03-10",
          "date_fin": "2024-04-08",
          "moyen_transport": "train",
          "salarie": "Jose Edwards",
          "fonction": "Délégué",
          "direction": "DRH"
      },
      {
          "id": 86,
          "num_odm": "904-3534",
          "destination": "Louga",
          "date_deb": "2024-04-23",
          "date_fin": "2024-05-22",
          "moyen_transport": "vehicule",
          "salarie": "Peggy Ortiz",
          "fonction": "Responsable Logistique",
          "direction": "Distribution"
      },
      {
          "id": 87,
          "num_odm": "920-8164",
          "destination": "Tambacounda",
          "date_deb": "2024-08-04",
          "date_fin": "2024-08-28",
          "moyen_transport": "train",
          "salarie": "Jacob Medina",
          "fonction": "Secrétaire",
          "direction": "DSI"
      },
      {
          "id": 88,
          "num_odm": "198-2153",
          "destination": "Ziguinchor",
          "date_deb": "2024-03-04",
          "date_fin": "2024-04-01",
          "moyen_transport": "train",
          "salarie": "Erin Barry",
          "fonction": "Consultant",
          "direction": "Transport"
      },
      {
          "id": 89,
          "num_odm": "520-3390",
          "destination": "Kaolack",
          "date_deb": "2024-10-06",
          "date_fin": "2024-10-19",
          "moyen_transport": "avion",
          "salarie": "Rachel Brooks",
          "fonction": "Délégué",
          "direction": "DSI"
      },
      {
          "id": 90,
          "num_odm": "433-1974",
          "destination": "Diourbel",
          "date_deb": "2024-10-10",
          "date_fin": "2024-11-08",
          "moyen_transport": "bus",
          "salarie": "James Ray",
          "fonction": "Directeur",
          "direction": "Distribution"
      },
      {
          "id": 91,
          "num_odm": "979-6202",
          "destination": "Tambacounda",
          "date_deb": "2024-01-05",
          "date_fin": "2024-01-26",
          "moyen_transport": "train",
          "salarie": "Colleen Hall",
          "fonction": "Secrétaire",
          "direction": "DSI"
      },
      {
          "id": 92,
          "num_odm": "930-5189",
          "destination": "Saint-Louis",
          "date_deb": "2024-12-10",
          "date_fin": "2024-12-20",
          "moyen_transport": "train",
          "salarie": "Miguel Cross",
          "fonction": "Délégué",
          "direction": "DSI"
      },
      {
          "id": 93,
          "num_odm": "853-2001",
          "destination": "Tambacounda",
          "date_deb": "2024-10-18",
          "date_fin": "2024-11-10",
          "moyen_transport": "train",
          "salarie": "Andrea Davis",
          "fonction": "Délégué",
          "direction": "Transport"
      },
      {
          "id": 94,
          "num_odm": "360-8552",
          "destination": "Ziguinchor",
          "date_deb": "2024-02-29",
          "date_fin": "2024-03-28",
          "moyen_transport": "train",
          "salarie": "Kenneth Brown",
          "fonction": "Délégué",
          "direction": "Transport"
      },
      {
          "id": 95,
          "num_odm": "702-2352",
          "destination": "Dakar",
          "date_deb": "2024-02-08",
          "date_fin": "2024-03-09",
          "moyen_transport": "vehicule",
          "salarie": "Matthew Luna",
          "fonction": "Délégué",
          "direction": "Transport"
      },
      {
          "id": 96,
          "num_odm": "585-5890",
          "destination": "Dakar",
          "date_deb": "2024-01-25",
          "date_fin": "2024-02-04",
          "moyen_transport": "train",
          "salarie": "Samantha Parks",
          "fonction": "Agent maîtrise",
          "direction": "Transport"
      },
      {
          "id": 97,
          "num_odm": "983-5706",
          "destination": "Louga",
          "date_deb": "2024-07-01",
          "date_fin": "2024-07-24",
          "moyen_transport": "bus",
          "salarie": "Sophia Baker",
          "fonction": "Responsable Logistique",
          "direction": "DSI"
      },
      {
          "id": 98,
          "num_odm": "849-4476",
          "destination": "Louga",
          "date_deb": "2024-02-05",
          "date_fin": "2024-02-16",
          "moyen_transport": "avion",
          "salarie": "Diamond Combs",
          "fonction": "Agent maîtrise",
          "direction": "Distribution"
      },
      {
          "id": 99,
          "num_odm": "457-6543",
          "destination": "Louga",
          "date_deb": "2024-06-18",
          "date_fin": "2024-07-06",
          "moyen_transport": "bus",
          "salarie": "Joseph Roth",
          "fonction": "Responsable Logistique",
          "direction": "DSI"
      },
      {
          "id": 100,
          "num_odm": "577-8820",
          "destination": "Tambacounda",
          "date_deb": "2024-02-06",
          "date_fin": "2024-02-25",
          "moyen_transport": "vehicule",
          "salarie": "Johnny Fisher",
          "fonction": "Secrétaire",
          "direction": "Distribution"
      }
  ]
}